quantumdl/__init__.py
quantumdl/adjoint.py
quantumdl/ansatz.py
quantumdl/bitmath.py
quantumdl/channel.py
quantumdl/circuit.py
quantumdl/communication.py
quantumdl/cutting.py
quantumdl/distributed.py
quantumdl/gate.py
quantumdl/layer.py
quantumdl/operation.py
quantumdl/optimizer.py
quantumdl/qasm3.py
quantumdl/qmath.py
quantumdl/qnn.py
quantumdl/qpd.py
quantumdl/state.py
quantumdl/utils.py
quantumdl/mbqc/__init__.py
quantumdl/mbqc/command.py
quantumdl/mbqc/operation.py
quantumdl/mbqc/pattern.py
quantumdl/mbqc/state.py
quantumdl/photonic/__init__.py
quantumdl/photonic/ansatz.py
quantumdl/photonic/channel.py
quantumdl/photonic/circuit.py
quantumdl/photonic/decompose.py
quantumdl/photonic/distributed.py
quantumdl/photonic/draw.py
quantumdl/photonic/gate.py
quantumdl/photonic/hafnian_.py
quantumdl/photonic/mapper.py
quantumdl/photonic/measurement.py
quantumdl/photonic/operation.py
quantumdl/photonic/qmath.py
quantumdl/photonic/state.py
quantumdl/photonic/tdm.py
quantumdl/photonic/torontonian_.py
quantumdl/photonic/utils.py
quantumdlearning-1.0.1.dist-info/LICENSE
quantumdlearning-1.0.1.dist-info/METADATA
quantumdlearning-1.0.1.dist-info/WHEEL
quantumdlearning-1.0.1.dist-info/top_level.txt
quantumdlearning-1.0.1.dist-info/RECORD
